
>       87: invokevirtual #392                // Method getVertexColors:(Lme/je
llysquid/mods/sodium/client/render/chunk/compile/pipeline/BlockRenderContext;Lm
e/jellysquid/mods/sodium/client/model/color/ColorProvider;Lme/jellysquid/mods/s
odium/client/model/quad/BakedQuadView;)[I
        90: astore        13
        92: aload_0
        93: aload_1
        94: aload         6
        96: aload         5
        98: aload_2
        99: aload         11
       101: aload         13
       103: aload         12
       105: invokevirtual #396                // Method writeGeometry:(Lme/jell
ysquid/mods/sodium/client/render/chunk/compile/pipeline/BlockRenderContext;Lme/
jellysquid/mods/sodium/client/render/chunk/compile/buffers/ChunkModelBuilder;Ln
et/minecraft/world/phys/Vec3;Lme/jellysquid/mods/sodium/client/render/chunk/ter
rain/material/Material;Lme/jellysquid/mods/sodium/client/model/quad/BakedQuadVi
ew;[ILme/jellysquid/mods/sodium/client/model/light/data/QuadLightData;)V
       108: aload         11
       110: invokeinterface #400,  1          // InterfaceMethod me/jellysquid/
mods/sodium/client/model/quad/BakedQuadView.getSprite:()Lnet/minecraft/client/r
enderer/texture/TextureAtlasSprite;
       115: astore        14
       117: aload         14
       119: ifnull        131
       122: aload         6
       124: aload         14
       126: invokeinterface #404,  2          // InterfaceMethod me/jellysquid/
mods/sodium/client/render/chunk/compile/buffers/ChunkModelBuilder.addSprite:(Ln
et/minecraft/client/renderer/texture/TextureAtlasSprite;)V
       131: iinc          9, 1
       134: goto          25
       137: return

    private me.jellysquid.mods.sodium.client.model.light.data.QuadLightData get
VertexLight(me.jellysquid.mods.sodium.client.render.chunk.compile.pipeline.Bloc
kRenderContext, me.jellysquid.mods.sodium.client.model.light.LightPipeline,
net.minecraft.core.Direction,
me.jellysquid.mods.sodium.client.model.quad.BakedQuadView);
      Code:
         0: aload_0
         1: getfield      #65                 // Field
quadLightData:Lme/jellysquid/mods/sodium/client/model/light/data/QuadLightData;
         4: astore        5
         6: aload_2
         7: aload         4
         9: aload_1
        10: invokevirtual #176                // Method me/jellysquid/mods/sodi
um/client/render/chunk/compile/pipeline/BlockRenderContext.pos:()Lnet/minecraft
/core/BlockPos;
        13: aload         5
        15: aload_3
        16: aload         4
        18: invokeinterface #416,  1          // InterfaceMethod me/jellysquid/
mods/sodium/client/model/quad/BakedQuadView.getLightFace:()Lnet/minecraft/core/
Direction;
        23: aload         4
        25: invokeinterface #419,  1          // InterfaceMethod
me/jellysquid/mods/sodium/client/model/quad/BakedQuadView.hasShade:()Z
        30: invokeinterface #423,  7          // InterfaceMethod me/jellysquid/
mods/sodium/client/model/light/LightPipeline.calculate:(Lme/jellysquid/mods/sod
ium/client/model/quad/ModelQuadView;Lnet/minecraft/core/BlockPos;Lme/jellysquid
/mods/sodium/client/model/light/data/QuadLightData;Lnet/minecraft/core/Directio
n;Lnet/minecraft/core/Direction;Z)V
        35: aload         5
        37: areturn

>   private int[] getVertexColors(me.jellysquid.mods.sodium.client.render.chunk
.compile.pipeline.BlockRenderContext, me.jellysquid.mods.sodium.client.model.co
lor.ColorProvider<net.minecraft.world.level.block.state.BlockState>,
me.jellysquid.mods.sodium.client.model.quad.BakedQuadView);
      Code:
         0: aload_0
         1: getfield      #73                 // Field quadColors:[I
         4: astore        4
         6: aload_2
         7: ifnull        71
        10: aload_3
        11: invokeinterface #428,  1          // InterfaceMethod
me/jellysquid/mods/sodium/client/model/quad/BakedQuadView.hasColor:()Z
        16: ifeq          71
        19: aload_2
        20: aload_1
        21: invokevirtual #432                // Method me/jellysquid/mods/sodi
um/client/render/chunk/compile/pipeline/BlockRenderContext.world:()Lme/jellysqu
id/mods/sodium/client/world/WorldSlice;
        24: aload_1
        25: invokevirtual #176                // Method me/jellysquid/mods/sodi
um/client/render/chunk/compile/pipeline/BlockRenderContext.pos:()Lnet/minecraft
/core/BlockPos;
        28: aload_1
        29: invokevirtual #154                // Method me/jellysquid/mods/sodi
um/client/render/chunk/compile/pipeline/BlockRenderContext.state:()Lnet/minecra
ft/world/level/block/state/BlockState;
        32: aload_3
        33: aload         4
        35: invokeinterface #436,  6          // InterfaceMethod me/jellysquid/
mods/sodium/client/model/color/ColorProvider.getColors:(Lme/jellysquid/mods/sod
ium/client/world/WorldSlice;Lnet/minecraft/core/BlockPos;Ljava/lang/Object;Lme/
jellysquid/mods/sodium/client/model/quad/ModelQuadView;[I)V
        40: iconst_0
        41: istore        5
        43: iload         5
        45: aload         4
        47: arraylength
        48: if_icmpge     68
        51: aload         4
        53: iload         5
        55: dup2
        56: iaload
        57: ldc_w         #438                // int -16777216
        60: ior
        61: iastore
        62: iinc          5, 1
        65: goto          43
        68: goto          77
        71: aload         4
        73: iconst_m1
        74: invokestatic  #444                // Method
java/util/Arrays.fill:([II)V
        77: aload         4
        79: areturn

    private void writeGeometry(me.jellysquid.mods.sodium.client.render.chunk.co
mpile.pipeline.BlockRenderContext, me.jellysquid.mods.sodium.client.render.chun
k.compile.buffers.ChunkModelBuilder, net.minecraft.world.phys.Vec3,
me.jellysquid.mods.sodium.client.render.chunk.terrain.material.Material,
me.jellysquid.mods.sodium.client.model.quad.BakedQuadView, int[],
me.jellysquid.mods.sodium.client.model.light.data.QuadLightData);
      Code:
         0: aload_0
         1: getfield      #290                // Field useReorienting:Z
         4: ifeq          23
         7: aload         7
         9: getfield      #449                // Field
me/jellysquid/mods/sodium/client/model/light/data/QuadLightData.br:[F
        12: aload         7
        14: getfield      #452                // Field
me/jellysquid/mods/sodium/client/model/light/data/QuadLightData.lm:[I
        17: invokestatic  #458                // Method me/jellysquid/mods/sodi
um/client/model/quad/properties/ModelQuadOrientation.orientByBrightness:([F[I)L
me/jellysquid/mods/sodium/client/model/quad/properties/ModelQuadOrientation;
        20: goto          26
        23: getstatic     #462                // Field me/jellysquid/mods/sodiu
m/client/model/quad/properties/ModelQuadOrientation.NORMAL:Lme/jellysquid/mods/
sodium/client/model/quad/properties/ModelQuadOrientation;
        26: astore        8
        28: aload_0
        29: getfield      #71                 // Field vertices:[Lme/jellysquid
/mods/sodium/client/render/chunk/vertex/format/ChunkVertexEncoder$Vertex;
        32: astore        9
        34: aload         5
        36: invokeinterface #466,  1          // InterfaceMethod me/jellysquid/
mods/sodium/client/model/quad/BakedQuadView.getNormalFace:()Lme/jellysquid/mods
/sodium/client/model/quad/properties/ModelQuadFacing;
        41: astore        10
        43: iconst_0
        44: istore        11
        46: iload         11
        48: iconst_4
        49: if_icmpge     256
        52: aload         8
        54: iload         11
        56: invokevirtual #473                // Method me/jellysquid/mods/sodi
um/client/model/quad/properties/ModelQuadOrientation.getVertexIndex:(I)I
        59: istore        12
        61: aload         9
        63: iload         11
        65: aaload
        66: astore        13
        68: aload         13
        70: aload_1
        71: invokevirtual #247                // Method me/jellysquid/mods/sodi
um/client/render/chunk/compile/pipeline/BlockRenderContext.origin:()Lorg/joml/V
ector3fc;
        74: invokeinterface #479,  1          // InterfaceMethod
org/joml/Vector3fc.x:()F
        79: aload         5
        81: iload         12
        83: invokeinterface #483,  2          // InterfaceMethod
me/jellysquid/mods/sodium/client/model/quad/BakedQuadView.getX:(I)F
        88: fadd
        89: aload_3
        90: invokevirtual #487                // Method
net/minecraft/world/phys/Vec3.m_7096_:()D
        93: d2f
        94: fadd
        95: putfield      #490                // Field me/jellysquid/mods/sodiu
m/client/render/chunk/vertex/format/ChunkVertexEncoder$Vertex.x:F
        98: aload         13
       100: aload_1
       101: invokevirtual #247                // Method me/jellysquid/mods/sodi
um/client/render/chunk/compile/pipeline/BlockRenderContext.origin:()Lorg/joml/V
ector3fc;
       104: invokeinterface #493,  1          // InterfaceMethod
org/joml/Vector3fc.y:()F
       109: aload         5
       111: iload         12
       113: invokeinterface #496,  2          // InterfaceMethod
me/jellysquid/mods/sodium/client/model/quad/BakedQuadView.getY:(I)F
       118: fadd
       119: aload_3
       120: invokevirtual #499                // Method
net/minecraft/world/phys/Vec3.m_7098_:()D
       123: d2f
       124: fadd
       125: putfield      #501                // Field me/jellysquid/mods/sodiu
m/client/render/chunk/vertex/format/ChunkVertexEncoder$Vertex.y:F
       128: aload         13